zfs_uploader/__init__.py
zfs_uploader/__main__.py
zfs_uploader/backup_db.py
zfs_uploader/config.py
zfs_uploader/job.py
zfs_uploader/snapshot_db.py
zfs_uploader/utils.py
zfs_uploader/zfs.py
zfs_uploader-0.9.0.dist-info/LICENSE
zfs_uploader-0.9.0.dist-info/METADATA
zfs_uploader-0.9.0.dist-info/WHEEL
zfs_uploader-0.9.0.dist-info/entry_points.txt
zfs_uploader-0.9.0.dist-info/top_level.txt
zfs_uploader-0.9.0.dist-info/RECORD
