Metadata-Version: 2.1
Name: zfs-uploader
Version: 0.9.0
Summary: ZFS snapshot to S3 uploader.
Home-page: https://github.com/ddebeau/zfs_uploader
Author: David Debeau
Author-email: ddebeau@gmail.com
Project-URL: Bug Tracker, https://github.com/ddebeau/zfs_uploader/issues
Classifier: Programming Language :: Python :: 3
Classifier: License :: OSI Approved :: MIT License
Classifier: Operating System :: POSIX :: Linux
Requires-Python: >=3.6
License-File: LICENSE
Requires-Dist: apscheduler >=3.6.3
Requires-Dist: boto3 >=1.16.20
Requires-Dist: click >=7.0
